jmapc/__init__.py
jmapc/__version__.py
jmapc/api.py
jmapc/auth.py
jmapc/client.py
jmapc/constants.py
jmapc/errors.py
jmapc/fastmail/__init__.py
jmapc/fastmail/maskedemail_methods.py
jmapc/fastmail/maskedemail_models.py
jmapc/logging.py
jmapc/methods/__init__.py
jmapc/methods/base.py
jmapc/methods/core.py
jmapc/methods/custom.py
jmapc/methods/email.py
jmapc/methods/email_submission.py
jmapc/methods/identity.py
jmapc/methods/mailbox.py
jmapc/methods/search_snippet.py
jmapc/methods/thread.py
jmapc/models/__init__.py
jmapc/models/email.py
jmapc/models/email_submission.py
jmapc/models/event.py
jmapc/models/identity.py
jmapc/models/mailbox.py
jmapc/models/models.py
jmapc/models/search_snippet.py
jmapc/models/thread.py
jmapc/py.typed
jmapc/ref.py
jmapc/serializer.py
jmapc/session.py
jmapc-0.2.23.dist-info/LICENSE
jmapc-0.2.23.dist-info/METADATA
jmapc-0.2.23.dist-info/WHEEL
jmapc-0.2.23.dist-info/RECORD
