Metadata-Version: 2.3
Name: jmapc
Version: 0.2.23
Summary: JMAP client library for Python
License: GPL-3.0-or-later
Author: Stephen Kent
Author-email: smkent@smkent.net
Requires-Python: >=3.9,<4.0
Classifier: Development Status :: 4 - Beta
Classifier: Operating System :: OS Independent
Classifier: Topic :: Communications :: Email :: Post-Office
Classifier: Topic :: Office/Business :: Groupware
Classifier: Topic :: Software Development :: Libraries :: Python Modules
Classifier: Typing :: Typed
Requires-Dist: brotli (>=1.0.9)
Requires-Dist: dataclasses-json
Requires-Dist: python-dateutil
Requires-Dist: requests
Requires-Dist: sseclient
